{"overview": "Best friends Marie and Alexia decide to spend a quiet weekend at Alexia's parents' secluded farmhouse. But on the night of their arrival, the girls' idyllic getaway turns into an endless night of horror.", "popularity": 16.142, "original_title": "Haute tension", "runtime": 90, "release_date": "2003-06-18", "vote_average": 6.745, "vote_count": 1173, "status": "Released", "tagline": "Hearts will bleed.", "spoken_languages": "it|en|fr", "cast": "C\u00e9cile de France|Ma\u00efwenn|Philippe Nahon|Andrei Finti|Oana Pellea", "id": 10226}