{"overview": "Determined to prove its superiority, a bio-engineered Pok\u00e9mon called Mewtwo lures Ash, Pikachu and others into a Pokemon match like none before.", "popularity": 28.439, "original_title": "\u5287\u5834\u7248\u30dd\u30b1\u30c3\u30c8\u30e2\u30f3\u30b9\u30bf\u30fc \u30df\u30e5\u30a6\u30c4\u30fc\u306e\u9006\u8972", "runtime": 85, "release_date": "1998-07-18", "vote_average": 6.91, "vote_count": 1341, "status": "Released", "tagline": "The Pok\u00e9mon match of all time is here.", "spoken_languages": "ja", "cast": "Rica Matsumoto|Ikue Otani|Mayumi Izuka|Satomi Korogi|Yuji Ueda", "id": 10228}