{"overview": "Dirty tricks stand to soil an ambitious young press spokesman's idealism in a cutthroat presidential campaign where 'victory' is relative.", "popularity": 15.301, "original_title": "The Ides of March", "runtime": 101, "release_date": "2011-09-24", "vote_average": 6.67, "vote_count": 2274, "status": "Released", "tagline": "Ambition seduces. Power corrupts.", "spoken_languages": "en", "cast": "Ryan Gosling|George Clooney|Philip Seymour Hoffman|Paul Giamatti|Evan Rachel Wood", "id": 10316}