{"overview": "Lifelong platonic friends Zack and Miri look to solve their respective cash-flow problems by making an adult film together. As the cameras roll, however, the duo begin to sense that they may have more feelings for each other than they previously thought.", "popularity": 30.52, "original_title": "Zack and Miri Make a Porno", "runtime": 102, "release_date": "2008-09-18", "vote_average": 6.307, "vote_count": 2207, "status": "Released", "tagline": "What would you do to get out of debt?", "spoken_languages": "en", "cast": "Elizabeth Banks|Seth Rogen|Craig Robinson|Gerry Bednob|Edward Janda", "id": 10358}