{"overview": "Lola receives a phone call from her boyfriend Manni. He lost 100,000 DM in a subway train that belongs to a very bad guy. She has 20 minutes to raise this amount and meet Manni. Otherwise, he will rob a store to get the money. Three different alternatives may happen depending on some minor event along Lola's run.", "popularity": 22.106, "original_title": "Lola rennt", "runtime": 81, "release_date": "1998-03-03", "vote_average": 7.321, "vote_count": 2022, "status": "Released", "tagline": "Every second of every day you're faced with a decision that can change your life.", "spoken_languages": "de|en|ja", "cast": "Franka Potente|Moritz Bleibtreu|Herbert Knaup|Nina Petri|Armin Rohde", "id": 104}