{"overview": "A streetwise man flees South Central Los Angeles, heading to the suburbs and his lottery-winner uncle and cousin, to avoid a neighborhood thug with a grudge who has just escaped from prison.", "popularity": 16.493, "original_title": "Next Friday", "runtime": 98, "release_date": "2000-01-12", "vote_average": 6.45, "vote_count": 513, "status": "Released", "tagline": "The suburbs make the hood look good.", "spoken_languages": "en", "cast": "Ice Cube|Mike Epps|Justin Pierce|John Witherspoon|Don Curry", "id": 10471}