{"overview": "At a sizable public college, high-minded student Eddy is forced to room with the slovenly Stuart, but the pair strike up a surprising friendship. When attractive co-ed Alex is assigned to live with the two male students because of her gender-neutral name, a roundabout love triangle ensues. Eddy secretly yearns for Stuart, who wants Alex, but she prefers Eddy. The complex situation leads to sexual experimentation and strained relationships.", "popularity": 12.58, "original_title": "Threesome", "runtime": 93, "release_date": "1994-04-08", "vote_average": 6.3, "vote_count": 205, "status": "Released", "tagline": "One girl. Two guys. Three possibilities.", "spoken_languages": "en", "cast": "Lara Flynn Boyle|Stephen Baldwin|Josh Charles|Alexis Arquette|Martha Gehman", "id": 10635}