{"overview": "Taran is an assistant pigkeeper with boyish dreams of becoming a great warrior. However, he has to put the daydreaming aside when his charge, an oracular pig named Hen Wen, is kidnapped by an evil lord known as the Horned King. The villain hopes Hen will show him the way to The Black Cauldron, which has the power to create a giant army of unstoppable soldiers.", "popularity": 27.384, "original_title": "The Black Cauldron", "runtime": 80, "release_date": "1985-07-24", "vote_average": 6.4, "vote_count": 1144, "status": "Released", "tagline": "Hidden by darkness. Guarded by witches. Discovered by a boy. Stolen by a king. Whoever owns it will rule the world. Or destroy it.", "spoken_languages": "ar|en|pt", "cast": "Grant Bardsley|Susan Sheridan|John Byner|Nigel Hawthorne|John Hurt", "id": 10957}