{"overview": "Six years ago, Michael Myers terrorized the town of Haddonfield, Illinois. He and his niece, Jamie Lloyd, have disappeared. Jamie was kidnapped by a bunch of evil druids who protect Michael Myers. And now, six years later, Jamie has escaped after giving birth to Michael's child. She runs to Haddonfield to get Dr. Loomis to help her again.", "popularity": 34.204, "original_title": "Halloween: The Curse of Michael Myers", "runtime": 88, "release_date": "1995-09-29", "vote_average": 5.2, "vote_count": 996, "status": "Released", "tagline": "Terror Never Rests in Peace.", "spoken_languages": "en", "cast": "Donald Pleasence|Paul Rudd|Marianne Hagan|Mitchell Ryan|Kim Darby", "id": 10987}