{"overview": "The story of the last Seal Child\u2019s journey home. After their mother\u2019s disappearance, Ben and Saoirse are sent to live with Granny in the city. When they resolve to return to their home by the sea, their journey becomes a race against time as they are drawn into a world Ben knows only from his mother\u2019s folktales. But this is no bedtime story; these fairy folk have been in our world far too long. It soon becomes clear to Ben that Saoirse is the key to their survival.", "popularity": 20.756, "original_title": "Song of the Sea", "runtime": 93, "release_date": "2014-09-06", "vote_average": 8.015, "vote_count": 1302, "status": "Released", "tagline": "Let the song of the sea sway your heart...", "spoken_languages": "en|gl|ga", "cast": "David Rawle|Lucy O'Connell|Brendan Gleeson|Fionnula Flanagan|Pat Shortt", "id": 110416}