{"overview": "The relationships among two pre-pubescent brothers and their estranged father are tested on a trip into the Russian wilderness.", "popularity": 9.772, "original_title": "\u0412\u043e\u0437\u0432\u0440\u0430\u0449\u0435\u043d\u0438\u0435", "runtime": 111, "release_date": "2003-06-25", "vote_average": 7.469, "vote_count": 494, "status": "Released", "tagline": "", "spoken_languages": "ru", "cast": "Vladimir Garin|Konstantin Lavronenko|Nataliya Vdovina|Ivan Dobronravov|Lazar Dubovik", "id": 11190}