{"overview": "When a serial killer interrupts the fun at the swanky Coconut Pete's Coconut Beach Resort -- a hedonistic island paradise for swingers --- it's up to the club's staff to stop the violence ... or at least hide it!", "popularity": 14.33, "original_title": "Club Dread", "runtime": 104, "release_date": "2004-02-27", "vote_average": 5.2, "vote_count": 338, "status": "Released", "tagline": "A vacation to die for.", "spoken_languages": "en", "cast": "Kevin Heffernan|Jay Chandrasekhar|Brittany Daniel|Bill Paxton|Steve Lemme", "id": 11217}