{"overview": "A transfer student at a rough high school tries joining the cheer-leading squad and finds that she not only has to face off against the head cheerleader, but also against her former school in preparation for a cheer-off competition.", "popularity": 0.894, "original_title": "Bring It On: All or Nothing", "runtime": 99, "release_date": "2006-07-18", "vote_average": 6.654, "vote_count": 739, "status": "Released", "tagline": "", "spoken_languages": "en", "cast": "Hayden Panettiere|Solange|Jake McDorman|Kiersten Warren|Emme Rylan", "id": 11211}