{"overview": "An on-the-scene documentary following the events of September 11, 2001 from an insider's view, through the lens of two French filmmakers who simply set out to make a movie about a rookie NYC fireman and ended up filming the tragic event that changed our lives forever.", "popularity": 6.908, "original_title": "9/11", "runtime": 128, "release_date": "2002-03-10", "vote_average": 7.791, "vote_count": 103, "status": "Released", "tagline": "The Filmmakers' Commemorative Edition", "spoken_languages": "en", "cast": "Tony Benatatos|Jamal Braithwaite|Joseph Casaliggi|James Hanlon|Joseph Pfeifer", "id": 11304}