{"overview": "Pinhead is trapped in the Pillar of Souls. Fortunately for him it is bought by a young playboy who owns his own nightclub. Pinhead busies himself escaping by getting the playboy to lure victims to his presence so he can use their blood. Once free, he seeks to destroy the puzzle box so he need never return to Hell, but a female reporter is investigating the grisly murders and stands in his way.", "popularity": 24.352, "original_title": "Hellraiser III: Hell on Earth", "runtime": 93, "release_date": "1992-09-11", "vote_average": 5.63, "vote_count": 671, "status": "Released", "tagline": "What started in hell, will end on Earth.", "spoken_languages": "en", "cast": "Terry Farrell|Doug Bradley|Kevin Bernhardt|Ken Carpenter|Paula Marshall", "id": 11569}