{"overview": "A young playboy who learns he has one month until he becomes infertile sets out to procreate as much as possible.", "popularity": 7.95, "original_title": "Not Suitable For Children", "runtime": 97, "release_date": "2012-07-12", "vote_average": 5.287, "vote_count": 93, "status": "Released", "tagline": "He never wanted to have kids until life kicked him where it counts", "spoken_languages": "en", "cast": "Ryan Kwanten|Sarah Snook|Ryan Corr|Bojana Novakovi\u0107|Laura Brent", "id": 120292}