{"overview": "The hilarity begins when professor Sherman Klump finds romance with fellow DNA specialist, Denise Gaines, and discovers a brilliant formula that reverses aging. But Sherman's thin and obnoxious alter ego, Buddy Love, wants out...and a big piece of the action. And when Buddy gets loose, things get seriously nutty.", "popularity": 24.895, "original_title": "Nutty Professor II: The Klumps", "runtime": 106, "release_date": "2000-07-27", "vote_average": 4.982, "vote_count": 1203, "status": "Released", "tagline": "The Klumps are back!", "spoken_languages": "en", "cast": "Eddie Murphy|Janet Jackson|Larry Miller|John Ales|Richard Gant", "id": 12107}