{"overview": "From Wichita to Dodge City, to the O.K. Corral in Tombstone, Wyatt Earp is taught that nothing matters more than family and the law. Joined by his brothers and Doc Holliday, Earp wages war on the dreaded Clanton and McLaury gangs.", "popularity": 21.51, "original_title": "Wyatt Earp", "runtime": 191, "release_date": "1994-06-24", "vote_average": 6.762, "vote_count": 755, "status": "Released", "tagline": "The epic story of love and adventure in a lawless land.", "spoken_languages": "en", "cast": "Kevin Costner|Dennis Quaid|Gene Hackman|David Andrews|Linden Ashby", "id": 12160}