{"overview": "Former mental patient Norman Bates is once again operating his infamous motel, where he keeps up the semblance of being sane and ordinary, but still holds on to some macabre habits. Eventually, Norman becomes interested in a troubled tenant who's been staying on a long-term basis and reminds him of someone from his past. As they begin a relationship, can Norman keep his demons in check?", "popularity": 15.343, "original_title": "Psycho III", "runtime": 93, "release_date": "1986-04-02", "vote_average": 5.585, "vote_count": 340, "status": "Released", "tagline": "Norman Bates is back to normal. But Mother's off her rocker again!", "spoken_languages": "en", "cast": "Anthony Perkins|Diana Scarwid|Jeff Fahey|Roberta Maxwell|Hugh Gillin", "id": 12662}