{"overview": "It's the year 2707. Earth's natural resources have all but been exhausted by mankind. Battles rage for the remainder between the competing Corporations. During one such battle the seal is broken and awakens an ancient and deadly machine that was once defeated thousands of years ago. The order that awaited its return must now lead a small group of soldiers to destroy it once and for all.", "popularity": 16.838, "original_title": "Mutant Chronicles", "runtime": 111, "release_date": "2008-08-07", "vote_average": 5.236, "vote_count": 420, "status": "Released", "tagline": "Welcome to the 23rd century.  The new dark ages.", "spoken_languages": "en", "cast": "Ron Perlman|Thomas Jane|Devon Aoki|Sean Pertwee|Benno F\u00fcrmann", "id": 13256}