{"overview": "Count Dracula adjourns to Earth, accompanied by Frankenstein's Monster, the Wolfman, the Mummy, and the Gillman. The uglies are in search of a powerful amulet that will grant them power to rule the world. Our heroes - the Monster Squad are the only ones daring to stand in their way.", "popularity": 15.498, "original_title": "The Monster Squad", "runtime": 82, "release_date": "1987-08-14", "vote_average": 6.7, "vote_count": 515, "status": "Released", "tagline": "You know who to call when you have ghosts but who do you call when you have monsters?", "spoken_languages": "de|en|pt", "cast": "Andr\u00e9 Gower|Robby Kiger|Stephen Macht|Duncan Regehr|Tom Noonan", "id": 13509}