{"overview": "A narcissistic TV weatherman, along with his attractive-but-distant producer, and his mawkish cameraman, is sent to report on Groundhog Day in the small town of Punxsutawney, where he finds himself repeating the same day over and over.", "popularity": 33.312, "original_title": "Groundhog Day", "runtime": 101, "release_date": "1993-02-11", "vote_average": 7.608, "vote_count": 7328, "status": "Released", "tagline": "He\u2019s having the worst day of his life\u2026 Over and over again.", "spoken_languages": "en|fr|it", "cast": "Bill Murray|Andie MacDowell|Chris Elliott|Stephen Tobolowsky|Brian Doyle-Murray", "id": 137}