{"overview": "A man accidentally gets into a time machine and travels back in time nearly an hour. Finding himself will be the first of a series of disasters of unforeseeable consequences.", "popularity": 11.214, "original_title": "Los cronocr\u00edmenes", "runtime": 92, "release_date": "2007-10-05", "vote_average": 7.019, "vote_count": 1143, "status": "Released", "tagline": "A trip back in time from the present to...", "spoken_languages": "es", "cast": "Karra Elejalde|Candela Fern\u00e1ndez|B\u00e1rbara Goenaga|Nacho Vigalondo|Juan Inciarte", "id": 14139}