{"overview": "Everyone always knew that Max had a wild imagination, but no one believed that his wildest creations -- a boy raised by watchful great white sharks and a girl with the force of a volcano -- were real. Now, these two pint-sized action masters will show Max that even an ordinary kid has what it takes to be extraordinary.", "popularity": 23.83, "original_title": "The Adventures of Sharkboy and Lavagirl", "runtime": 92, "release_date": "2005-06-10", "vote_average": 5.142, "vote_count": 1378, "status": "Released", "tagline": "Smaller heroes. Just as super.", "spoken_languages": "en", "cast": "Taylor Lautner|Taylor Dooley|Cayden Boyd|David Arquette|Kristin Davis", "id": 14199}