{"overview": "Two business executives--one an avowed misogynist, the other recently emotionally wounded by his love interest--set out to exact revenge on the female gender by seeking out the most innocent, uncorrupted girl they can find and ruining her life.", "popularity": 7.581, "original_title": "In the Company of Men", "runtime": 97, "release_date": "1997-03-28", "vote_average": 6.7, "vote_count": 132, "status": "Released", "tagline": "Are all men bastards...or just misunderstood?", "spoken_languages": "en", "cast": "Aaron Eckhart|Stacy Edwards|Matt Malloy|Michael Martin|Mark Rector", "id": 14585}