{"overview": "Tromaville has a monstrous new hero. The Toxic Avenger is born when mop boy Melvin Junko falls into a vat of toxic waste. Now evildoers will have a lot to lose.", "popularity": 13.674, "original_title": "The Toxic Avenger", "runtime": 82, "release_date": "1984-05-01", "vote_average": 6.269, "vote_count": 476, "status": "Released", "tagline": "He was 98lbs. of solid nerd until he became...", "spoken_languages": "en", "cast": "Mark Torgl|Mitch Cohen|Andree Maranda|Pat Ryan|Cindy Manion", "id": 15239}