{"overview": "Teacher Linda Sinclair balances her staid home life with an incredible passion for her subject, but her routine is forever altered when a former star pupil and his unsupportive father reenter her life.", "popularity": 11.137, "original_title": "The English Teacher", "runtime": 91, "release_date": "2013-05-16", "vote_average": 5.612, "vote_count": 326, "status": "Released", "tagline": "Refuse To Live Life By The Book", "spoken_languages": "en", "cast": "Julianne Moore|Michael Angarano|Greg Kinnear|Lily Collins|Fiona Shaw", "id": 174321}