{"overview": "Phoenix cop Ben Shockley is well on his way to becoming a derelict when he is assigned to transport a witness from Las Vegas. The witness turns out to be a belligerent prostitute with mob ties\u2014and incriminating information regarding a high-ranking figure.", "popularity": 12.021, "original_title": "The Gauntlet", "runtime": 109, "release_date": "1977-12-17", "vote_average": 6.568, "vote_count": 462, "status": "Released", "tagline": "Clint Eastwood is the man in the middle of The Gauntlet", "spoken_languages": "en", "cast": "Clint Eastwood|Sondra Locke|Pat Hingle|William Prince|Bill McKinney", "id": 17689}