{"overview": "Captain Jack Sparrow crosses paths with a woman from his past, and he's not sure if it's love -- or if she's a ruthless con artist who's using him to find the fabled Fountain of Youth. When she forces him aboard the Queen Anne's Revenge, the ship of the formidable pirate Blackbeard, Jack finds himself on an unexpected adventure in which he doesn't know who to fear more: Blackbeard or the woman from his past.", "popularity": 107.886, "original_title": "Pirates of the Caribbean: On Stranger Tides", "runtime": 137, "release_date": "2011-05-15", "vote_average": 6.538, "vote_count": 13207, "status": "Released", "tagline": "Live Forever Or Die Trying.", "spoken_languages": "en|es", "cast": "Johnny Depp|Pen\u00e9lope Cruz|Geoffrey Rush|Ian McShane|Kevin McNally", "id": 1865}