{"overview": "In the midst of World War II, Sherlock Holmes rescues the Swiss inventor of a new bomb-sight from the Gestapo and brings him to England, where he shortly falls into the clutches of Professor Moriarty.", "popularity": 11.25, "original_title": "Sherlock Holmes and the Secret Weapon", "runtime": 68, "release_date": "1942-12-25", "vote_average": 6.312, "vote_count": 101, "status": "Released", "tagline": "Suspense!  Thrills!  Adventure!", "spoken_languages": "en", "cast": "Basil Rathbone|Nigel Bruce|Lionel Atwill|William Post Jr.|Kaaren Verne", "id": 18706}