{"overview": "A reporter's dream of becoming a news anchor is compromised after a one-night stand leaves her stranded in downtown L.A. without a phone, car, ID or money - and only 8 hours to make it to the most important job interview of her life.", "popularity": 12.744, "original_title": "Walk of Shame", "runtime": 95, "release_date": "2014-05-02", "vote_average": 6.0, "vote_count": 1343, "status": "Released", "tagline": "Awesome night. Epic aftermath.", "spoken_languages": "en", "cast": "Elizabeth Banks|James Marsden|Gillian Jacobs|Sarah Wright|Ethan Suplee", "id": 187596}