{"overview": "A man coping with the institutionalization of his wife because of Alzheimer's disease faces an epiphany when she transfers her affections to another man, a wheel chair-bound mute who also is a patient at the nursing home.", "popularity": 8.252, "original_title": "Away from Her", "runtime": 110, "release_date": "2007-05-04", "vote_average": 7.0, "vote_count": 200, "status": "Released", "tagline": "It's never too late to become what you might have been.", "spoken_languages": "en", "cast": "Gordon Pinsent|Julie Christie|Michael Murphy|Olympia Dukakis|Kristen Thomson", "id": 1919}