{"overview": "In the questionable town of Deer Meadow, Washington, FBI Agent Desmond inexplicably disappears while hunting for the man who murdered a teen girl. The killer is never apprehended, and, after experiencing dark visions and supernatural encounters, Agent Dale Cooper chillingly predicts that the culprit will claim another life. Meanwhile, in the more cozy town of Twin Peaks, hedonistic beauty Laura Palmer hangs with lowlifes and seems destined for a grisly fate.", "popularity": 25.299, "original_title": "Twin Peaks: Fire Walk with Me", "runtime": 135, "release_date": "1992-06-03", "vote_average": 7.352, "vote_count": 1740, "status": "Released", "tagline": "Meet Laura Palmer... In a town where nothing is as it seems... And everyone has something to hide.", "spoken_languages": "en", "cast": "Sheryl Lee|Ray Wise|M\u00e4dchen Amick|Dana Ashbrook|Phoebe Augustine", "id": 1923}