{"overview": "Maurizio Merli stars as a hatchet-wielding bounty hunter with a dark past and an even more desperate future. But when he disrupts the balance of power in a corrupt mining town, he unleashes a firestorm of brutality, betrayal and cold-blooded murder. Now, one man stalks a savage land where justice walks a razor and no bullets slice deeper than vengeance. He is A MAN CALLED BLADE.", "popularity": 5.307, "original_title": "Mannaja", "runtime": 96, "release_date": "1977-08-13", "vote_average": 6.6, "vote_count": 30, "status": "Released", "tagline": "Sharp shoots, gun and axe with great accuracy!", "spoken_languages": "it", "cast": "Maurizio Merli|John Steiner|Philippe Leroy|Sonja Jeannine|Salvatore Puntillo", "id": 19946}