{"overview": "In 2035, where robots are commonplace and abide by the three laws of robotics, a technophobic cop investigates an apparent suicide. Suspecting that a robot may be responsible for the death, his investigation leads him to believe that humanity may be in danger.", "popularity": 35.522, "original_title": "I, Robot", "runtime": 115, "release_date": "2004-07-15", "vote_average": 6.94, "vote_count": 11049, "status": "Released", "tagline": "Laws are made to be broken.", "spoken_languages": "en", "cast": "Will Smith|Bridget Moynahan|Alan Tudyk|James Cromwell|Bruce Greenwood", "id": 2048}