{"overview": "In 1934, the second most lucrative business in New York City was running 'the numbers'. When Madam Queen\u2014the powerful woman who runs the scam in Harlem\u2014is arrested, Ellsworth 'Bumpy' Johnson takes over the business and must resist an invasion from a merciless mobster.", "popularity": 14.722, "original_title": "Hoodlum", "runtime": 130, "release_date": "1997-08-27", "vote_average": 6.33, "vote_count": 165, "status": "Released", "tagline": "Power is measured in enemies.", "spoken_languages": "en", "cast": "Laurence Fishburne|Tim Roth|Vanessa Williams|Andy Garc\u00eda|Cicely Tyson", "id": 22073}