{"overview": "Two twelve-year-old boys, Romeo and Gavin, undergo an extraordinary test of character and friendship when Morell, a naive but eccentric and dangerous stranger, comes between them. Morell befriends with the two boys and later asks them to help him pursue Romeo's beautiful elder sister. He gradually becomes more violent after she rejects him.", "popularity": 3.96, "original_title": "A Room for Romeo Brass", "runtime": 90, "release_date": "1999-08-23", "vote_average": 6.962, "vote_count": 52, "status": "Released", "tagline": "", "spoken_languages": "en", "cast": "Paddy Considine|Andrew Shim|Frank Harper|Vicky McClure|Johann Myers", "id": 22908}