{"overview": "Convinced that his family\u2019s blood is tainted by generations of evil, Roderick Usher is hell-bent on destroying his sister Madeline\u2019s wedding to prevent the cursed Usher bloodline from extending any further. When her fianc\u00e9, Philip Winthrop, arrives at the crumbling family estate to claim his bride, Roderick goes to ruthless lengths to keep them apart. And Philip soon discovers that, for the Ushers, their house is more than just a home\u2014it\u2019s their tomb!", "popularity": 14.071, "original_title": "House of Usher", "runtime": 79, "release_date": "1960-07-20", "vote_average": 6.596, "vote_count": 271, "status": "Released", "tagline": "Edgar Allan Poe's demonic tale of The Ungodly... The Evil House of Usher", "spoken_languages": "en", "cast": "Vincent Price|Mark Damon|Myrna Fahey|Harry Ellerbe|David Andar", "id": 23439}