{"overview": "New Yorkers Paul and Meryl Morgan seem to have it all -- except that their marriage is crumbling around them. But their romantic woes are small compared to the trouble they find themselves in after witnessing a murder. To protect them from an assassin, federal agents whisk away Paul and Meryl to a small town in Wyoming, where their marriage will crash and burn, or their passion will reignite.", "popularity": 12.92, "original_title": "Did You Hear About the Morgans?", "runtime": 103, "release_date": "2009-12-17", "vote_average": 5.344, "vote_count": 900, "status": "Released", "tagline": "We're not in Manhattan anymore.", "spoken_languages": "uk|ru|it|en|es", "cast": "Hugh Grant|Sarah Jessica Parker|Sam Elliott|Mary Steenburgen|Elisabeth Moss", "id": 24438}