{"overview": "This real-life thriller tells the story of one of Israel\u2019s prized intelligence sources, recruited to spy on his own people for more than a decade. Focusing on the complex relationship with his handler, The Green Prince is a gripping account of terror, betrayal, and unthinkable choices, along with a friendship that defies all boundaries.", "popularity": 5.116, "original_title": "The Green Prince", "runtime": 99, "release_date": "2014-01-16", "vote_average": 7.316, "vote_count": 38, "status": "Released", "tagline": "A courageous mission. A deadly game. An extraordinary friendship.", "spoken_languages": "he|en", "cast": "Mosab Hassan Yousef|Gonen Ben Yitzhak|Sheikh Hassan Yousef", "id": 250798}