{"overview": "When Kylie Bucknell is sentenced to home detention, she's forced to come to terms with her unsociable behaviour, her blabbering mother and a hostile spirit who seems less than happy about the new living arrangement.", "popularity": 9.728, "original_title": "Housebound", "runtime": 109, "release_date": "2014-09-04", "vote_average": 6.591, "vote_count": 782, "status": "Released", "tagline": "Terror Gets Domesticated", "spoken_languages": "en", "cast": "Morgana O'Reilly|Rima Te Wiata|Glen-Paul Waru|Ross Harper|Cameron Rhodes", "id": 253306}