{"overview": "Batman must face his most ruthless nemesis when a deformed madman calling himself \"The Joker\" seizes control of Gotham's criminal underworld.", "popularity": 43.649, "original_title": "Batman", "runtime": 126, "release_date": "1989-06-21", "vote_average": 7.217, "vote_count": 7206, "status": "Released", "tagline": "Have you ever danced with the devil in the pale moonlight?", "spoken_languages": "en|fr", "cast": "Jack Nicholson|Kim Basinger|Michael Keaton|Michael Gough|Jerry Hall", "id": 268}