{"overview": "A high school valedictorian who gets baked with the local stoner finds himself the subject of a drug test. The situation causes him to concoct an ambitious plan to get his entire graduating class to face the same fate, and fail.", "popularity": 11.207, "original_title": "High School", "runtime": 99, "release_date": "2010-06-03", "vote_average": 5.676, "vote_count": 137, "status": "Released", "tagline": "Random drug tests? You just can't study for them.", "spoken_languages": "en", "cast": "Adrien Brody|Matt Bush|Sean Marquette|Colin Hanks|Michael Chiklis", "id": 27584}