{"overview": "Paul, a teenager in the underground scene of early-nineties Paris, forms a DJ collective with his friends and together they plunge into the nightlife of sex, drugs, and endless music.", "popularity": 10.105, "original_title": "Eden", "runtime": 131, "release_date": "2014-11-19", "vote_average": 5.809, "vote_count": 118, "status": "Released", "tagline": "When You Start A Revolution, The Hardest Beat To Find Is Your Own", "spoken_languages": "en|fr", "cast": "F\u00e9lix de Givry|Pauline \u00c9tienne|Vincent Macaigne|Hugo Conzelmann|Zita Hanrot", "id": 283330}