{"overview": "Murphy is an American living in Paris who enters a highly sexually and emotionally charged relationship with the unstable Electra. Unaware of the seismic effect it will have on their relationship, they invite their pretty neighbor into their bed.", "popularity": 22.874, "original_title": "Love", "runtime": 134, "release_date": "2015-07-06", "vote_average": 6.461, "vote_count": 2266, "status": "Released", "tagline": "", "spoken_languages": "en", "cast": "Karl Glusman|Aomi Muyock|Klara Kristin|Ugo Fox|Juan Saavedra", "id": 292431}