{"overview": "Baron Victor Frankenstein has discovered life's secret and unleashed a blood-curdling chain of events resulting from his creation: a cursed creature with a horrid face \u2014 and a tendency to kill.", "popularity": 15.292, "original_title": "The Curse of Frankenstein", "runtime": 83, "release_date": "1957-05-20", "vote_average": 6.781, "vote_count": 260, "status": "Released", "tagline": "The creature created by man and forgotten by nature!", "spoken_languages": "en", "cast": "Peter Cushing|Hazel Court|Robert Urquhart|Christopher Lee|Melvyn Hayes", "id": 3079}