{"overview": "In this classic French satire, Louis, a convict, escapes from prison and takes on legitimate work, making his way up in the business world. Eventually becoming the head of a successful factory, Louis opts to modernize his company with mechanical innovations. But when his friend \u00c9mile finally leaves jail years later and reunites with Louis, the past catches up with them. The two, worried about being apprehended by police, long to flee the confines of industry.", "popularity": 7.484, "original_title": "\u00c0 nous la libert\u00e9", "runtime": 95, "release_date": "1931-12-18", "vote_average": 7.1, "vote_count": 84, "status": "Released", "tagline": "", "spoken_languages": "fr", "cast": "Henri Marchand|Raymond Cordy|Rolla France|Paul Ollivier|Jacques Shelly", "id": 31514}