{"overview": "A decade ago, curler Chris Cutter disappeared suddenly on the verge of stardom, dropping his curling stones to the bottom of a lake and leaving his fianc\u00e9e, Julie Foley, at the altar. But when his former coach dies, Cutter returns home for the funeral and attempts to fulfill the man's last wishes. The team is reunited under Cutter's estranged dad, Gordon \u2014 himself a former curling star \u2014 for a final attempt at glory.", "popularity": 3.865, "original_title": "Men with Brooms", "runtime": 102, "release_date": "2002-09-20", "vote_average": 5.271, "vote_count": 24, "status": "Released", "tagline": "There's More Than One Way To Sweep a Woman Off Her Feet.", "spoken_languages": "en", "cast": "James B. Douglas|Molly Parker|Paul Gross|Barbara Gordon|Michelle Nolden", "id": 34341}