{"overview": "With a cheeky, down-to-earth charm that appeals to both children and adults, the series \u2013 beginning with 'Vinnie-Pukh (1969)' \u2013 has since developed something of a cult following, and are considered by many to decisively surpass their Disney counterparts, however uneasily they may fit into the official canon. The animation itself is somewhat coarse and minimalistic, but this all adds to the charm of it all, with the story and characters coming to life as though they have just stepped out of a picture book.", "popularity": 6.636, "original_title": "\u0412\u0438\u043d\u043d\u0438-\u041f\u0443\u0445", "runtime": 11, "release_date": "1969-01-01", "vote_average": 7.2, "vote_count": 130, "status": "Released", "tagline": "", "spoken_languages": "ru", "cast": "Evgeni Leonov|Iya Savvina|Vladimir Osenev", "id": 36161}