{"overview": "A Southern California kid named Calvin Fuller is magically transported to the medieval kingdom of Camelot through a crack in the ground caused by an earthquake. Once there, he learns he was summoned by the wizard Merlin, who needs Calvin to save Camelot. Using dazzling modern inventions, can Calvin help King Arthur retain his crown and thwart the evil Lord Belasco?", "popularity": 9.906, "original_title": "A Kid in King Arthur's Court", "runtime": 89, "release_date": "1995-08-11", "vote_average": 4.804, "vote_count": 156, "status": "Released", "tagline": "Joust Do It.", "spoken_languages": "en", "cast": "Thomas Ian Nicholas|Joss Ackland|Art Malik|Daniel Craig|Kate Winslet", "id": 37108}