{"overview": "A judge gives con-man Tom Turner a choice\u2014a jail sentence, or a year of honest work. But when he gets a job in the U.S. Post Office's dead letter office, he starts a Good Samaritan con by answering letters written to God. His seemingly virtuous work inspires his co-workers to do the same, but their good deeds are frowned upon by the postmaster general\u2014and the cops.", "popularity": 7.628, "original_title": "Dear God", "runtime": 112, "release_date": "1996-11-01", "vote_average": 5.5, "vote_count": 56, "status": "Released", "tagline": "Many people write to God. Somebody is answering.", "spoken_languages": "en|it", "cast": "Greg Kinnear|Laurie Metcalf|Maria Pitillo|Tim Conway|H\u00e9ctor Elizondo", "id": 38554}