{"overview": "A black hole hits North Wisconsin and opens a door to other dimensions. Giant 15 meter spiders emerge from it, who have an appetite for human flesh! Dr. Jenny Langer and Dr. Vance from NASA try to save the world.", "popularity": 5.931, "original_title": "The Giant Spider Invasion", "runtime": 84, "release_date": "1975-10-01", "vote_average": 4.007, "vote_count": 72, "status": "Released", "tagline": "Creeping!...Crawling!...Crushing!", "spoken_languages": "en", "cast": "Steve Brodie|Barbara Hale|Robert Easton|Leslie Parrish|Alan Hale Jr.", "id": 39154}