{"overview": "After her fiancee admits to infidelity while on a business trip in France, a woman attempts to get her lover back and marry him by traveling to Paris despite her crippling fear of flying.  On the way she unwittingly smuggles something of value that has a charming crook chasing her across France as she chases after her future husband.", "popularity": 15.521, "original_title": "French Kiss", "runtime": 111, "release_date": "1995-05-05", "vote_average": 6.464, "vote_count": 659, "status": "Released", "tagline": "Kate's stuck in a place where anything can happen with a guy who'll make sure that it does.", "spoken_languages": "fr|en", "cast": "Meg Ryan|Kevin Kline|Timothy Hutton|Jean Reno|Adam Brooks", "id": 397}