{"overview": "Advertising executive Nick Marshall is as cocky as they come, but what happens to a chauvinistic guy when he can suddenly hear what women are thinking? Nick gets passed over for a promotion, but after an accident enables him to hear women's thoughts, he puts his newfound talent to work against Darcy, his new boss, who seems to be infatuated with him.", "popularity": 32.811, "original_title": "What Women Want", "runtime": 127, "release_date": "2000-12-15", "vote_average": 6.436, "vote_count": 3637, "status": "Released", "tagline": "He has the power to hear everything women are thinking. Finally... a man is listening.", "spoken_languages": "en|fr", "cast": "Mel Gibson|Helen Hunt|Marisa Tomei|Alan Alda|Ashley Johnson", "id": 3981}