{"overview": "A first person narrative of the exploits of a gay serial killer in deeply disturbing, controversial drama about violence, sexuality, and the imagination. Dennis, the main character, whose lead we follow on this path between what is real and what we can only hope is surreal. His friends attempt to determine if he's truly a psychopath.", "popularity": 2.375, "original_title": "Frisk", "runtime": 88, "release_date": "1996-03-22", "vote_average": 4.0, "vote_count": 12, "status": "Released", "tagline": "How far can a sexual fantasy go?", "spoken_languages": "en", "cast": "Michael Gunther|Craig Chester|Michael Stock|Raoul O'Connell|Jaie Laplante", "id": 40926}