{"overview": "In 1935, when his train is stopped by deep snow, detective Hercule Poirot is called on to solve a murder that occurred in his car the night before.", "popularity": 24.367, "original_title": "Murder on the Orient Express", "runtime": 128, "release_date": "1974-11-22", "vote_average": 7.146, "vote_count": 1284, "status": "Released", "tagline": "The greatest cast of suspicious characters ever involved in murder.", "spoken_languages": "sv|en|fr|de|tr|it", "cast": "Albert Finney|Lauren Bacall|Martin Balsam|Ingrid Bergman|Jacqueline Bisset", "id": 4176}