{"overview": "Guido Anselmi, a film director, finds himself creatively barren at the peak of his career. Urged by his doctors to rest, Anselmi heads for a luxurious resort, but a sorry group gathers\u2014his producer, staff, actors, wife, mistress, and relatives\u2014each one begging him to get on with the show. In retreat from their dependency, he fantasizes about past women and dreams of his childhood.", "popularity": 20.664, "original_title": "8\u00bd", "runtime": 139, "release_date": "1963-02-14", "vote_average": 8.164, "vote_count": 2083, "status": "Released", "tagline": "A picture that goes beyond what men think about - because no man ever thought about it in quite this way!", "spoken_languages": "de|en|fr|it", "cast": "Marcello Mastroianni|Claudia Cardinale|Anouk Aim\u00e9e|Sandra Milo|Rossella Falk", "id": 422}