{"overview": "Leo is a middle-aged writer of popular romantic novels who writes under a pseudonym, but despises her own work. At home, her husband, who works overseas, is distant both physically and emotionally. As she reevaluates her life and writing, Leo is led to an unexpected relationship with Angel, a sensitive newspaper editor.", "popularity": 9.844, "original_title": "La flor de mi secreto", "runtime": 103, "release_date": "1995-09-22", "vote_average": 6.83, "vote_count": 203, "status": "Released", "tagline": "Every woman has a secret...", "spoken_languages": "fr|es", "cast": "Marisa Paredes|Juan Echanove|Carme Elias|Rossy de Palma|Chus Lampreave", "id": 4307}