{"overview": "\"If I could work my will, every idiot that goes about with \u2018Merry Christmas\u2019 on his lips would be boiled with his own pudding and buried with a stake of holly in his heart\" So spoke the immortal words of Christmas\u2019 most famous miser, Charles Dicken\u2019s Ebenezer Scrooge. Too mean to join in with the festivities; he sits alone on Christmas Eve. The scene is set for a visitation by the ghost of his late business partner, Marley, now bound to earth by eternal chains and his introduction to the Ghosts of Christmas Past, Present and Future. For it is they who will take him through his life to face the truth about himself\u2026", "popularity": 2.373, "original_title": "A Christmas Carol", "runtime": 58, "release_date": "1977-12-24", "vote_average": 6.3, "vote_count": 10, "status": "Released", "tagline": "Being a Ghost Story of Christmas", "spoken_languages": "en", "cast": "Michael Hordern|John Le Mesurier|Bernard Lee|Patricia Quinn|Carol MacReady", "id": 45697}