{"overview": "Harry Donovan is an art forger who paints fake Rembrandt picture for $500,000. The girl he meets and gets into bed with in Paris, Marieke, turns out to be an arts expert Harry's clients are using to check the counterfeit picture he painted.", "popularity": 7.339, "original_title": "Incognito", "runtime": 108, "release_date": "1997-11-14", "vote_average": 5.8, "vote_count": 50, "status": "Released", "tagline": "Harry Donovan is a master in the art of deception... trapped in a lie so perfect even the truth can't save him.", "spoken_languages": "en|pt", "cast": "Jason Patric|Ir\u00e8ne Jacob|Ian Richardson|Rod Steiger|Thomas Lockyer", "id": 45928}