{"overview": "Following the death of District Attorney Harvey Dent, Batman assumes responsibility for Dent's crimes to protect the late attorney's reputation and is subsequently hunted by the Gotham City Police Department. Eight years later, Batman encounters the mysterious Selina Kyle and the villainous Bane, a new terrorist leader who overwhelms Gotham's finest. The Dark Knight resurfaces to protect a city that has branded him an enemy.", "popularity": 67.768, "original_title": "The Dark Knight Rises", "runtime": 165, "release_date": "2012-07-17", "vote_average": 7.777, "vote_count": 21467, "status": "Released", "tagline": "The Legend Ends", "spoken_languages": "en", "cast": "Christian Bale|Michael Caine|Gary Oldman|Anne Hathaway|Tom Hardy", "id": 49026}