{"overview": "Before Charles Xavier and Erik Lensherr took the names Professor X and Magneto, they were two young men discovering their powers for the first time. Before they were arch-enemies, they were closest of friends, working together with other mutants (some familiar, some new), to stop the greatest threat the world has ever known.", "popularity": 2.561, "original_title": "X-Men: First Class", "runtime": 132, "release_date": "2011-06-01", "vote_average": 7.296, "vote_count": 12047, "status": "Released", "tagline": "Witness the moment that will change our world.", "spoken_languages": "de|en|es|fr|ru", "cast": "James McAvoy|Michael Fassbender|Kevin Bacon|Rose Byrne|Jennifer Lawrence", "id": 49538}