{"overview": "On the afternoon of July 1, 1981, Los Angeles police responded to a distress call on Wonderland Avenue and discovered a grisly quadruple homicide. The police investigation that followed uncovered two versions of the events leading up to the brutal murders - both involving legendary porn actor John Holmes.", "popularity": 11.313, "original_title": "Wonderland", "runtime": 104, "release_date": "2003-10-23", "vote_average": 6.042, "vote_count": 239, "status": "Released", "tagline": "Sex, drugs, murder. Welcome to L.A.", "spoken_languages": "en", "cast": "Val Kilmer|Dylan McDermott|Kate Bosworth|Josh Lucas|Lisa Kudrow", "id": 4997}