{"overview": "Pepe Benengeli is a second-class cyclist, only there to support the star member of the team. This summer he is participating in the Tour of Spain, which passes through the streets of his hometown of Andalusia. In a coincidence, his brother and ex-girlfriend are getting married on the same day as the climax of the race. Pepe, who left his hometown after suffering a breakdown, is determined to achieve something special on this day.", "popularity": 6.656, "original_title": "\u8304\u5b50 \u30a2\u30f3\u30c0\u30eb\u30b7\u30a2\u306e\u590f", "runtime": 47, "release_date": "2003-06-26", "vote_average": 7.095, "vote_count": 20, "status": "Released", "tagline": "", "spoken_languages": "ja", "cast": "Yo Oizumi|Eiko Koike|Minoru Hirano|Ogata Aikou|Hiroaki Hirata", "id": 60843}