{"overview": "A wealthy playboy named Bruce Wayne and a Chicago cop named Jim Gordon both return to Gotham City where their lives unexpectedly intersect.", "popularity": 24.416, "original_title": "Batman: Year One", "runtime": 64, "release_date": "2011-09-27", "vote_average": 7.279, "vote_count": 866, "status": "Released", "tagline": "A merciless crime turns a man into an outlaw.", "spoken_languages": "en|pt", "cast": "Ben McKenzie|Bryan Cranston|Eliza Dushku|Jon Polito|Alex Rocco", "id": 69735}