{"overview": "For five men, the opportunity to share a penthouse in the city -- in which to carry on extramarital affairs -- is a dream come true, until the dead body of an unknown woman turns up. Realizing that her killer must be one of their group, the men are gripped by paranoia as each one suspects another. Friendships are tested, loyalties are questioned, and marriages crumble while fear and suspicion run rampant.", "popularity": 35.56, "original_title": "The Loft", "runtime": 108, "release_date": "2014-10-14", "vote_average": 6.417, "vote_count": 1361, "status": "Released", "tagline": "The right place to do wrong.", "spoken_languages": "en", "cast": "Karl Urban|James Marsden|Wentworth Miller|Eric Stonestreet|Matthias Schoenaerts", "id": 72784}