{"overview": "To test its top-secret Human Hibernation Project, the Pentagon picks the most average Americans it can find - an Army private and a prostitute - and sends them to the year 2505 after a series of freak events. But when they arrive, they find a civilization so dumbed-down that they're the smartest people around.", "popularity": 39.769, "original_title": "Idiocracy", "runtime": 84, "release_date": "2006-09-01", "vote_average": 6.306, "vote_count": 2595, "status": "Released", "tagline": "In the future, intelligence is extinct.", "spoken_languages": "en", "cast": "Luke Wilson|Maya Rudolph|Dax Shepard|Terry Crews|Anthony 'Citric' Campos", "id": 7512}