{"overview": "Legless Southern inventor Dr. Arliss Loveless plans to rekindle the Civil War by assassinating President U.S. Grant. Only two men can stop him: gunfighter James West and master-of-disguise and inventor Artemus Gordon. The two must team up to thwart Loveless' plans.", "popularity": 27.886, "original_title": "Wild Wild West", "runtime": 106, "release_date": "1999-06-30", "vote_average": 5.322, "vote_count": 3097, "status": "Released", "tagline": "It's a whole new west.", "spoken_languages": "en", "cast": "Will Smith|Kevin Kline|Kenneth Branagh|Salma Hayek Pinault|M. Emmet Walsh", "id": 8487}