{"overview": "An early example of ultra-realism, this movie contrasts the quiet, bucolic life in the outskirts of Paris with the harsh, gory conditions inside the nearby slaughterhouses. Describes the fate of the animals and that of the workers in graphic detail.", "popularity": 3.879, "original_title": "Le sang des b\u00eates", "runtime": 23, "release_date": "1949-01-01", "vote_average": 7.507, "vote_count": 71, "status": "Released", "tagline": "", "spoken_languages": "fr", "cast": "Georges Hubert|Nicole Ladmiral|Alfred Macquart|Maurice Griselle|Andr\u00e9 Brunier", "id": 91262}