{"overview": "Maverick is a gambler who would rather con someone than fight them, and needs an additional three thousand dollars in order to enter a winner-takes-all poker game that begins in a few days, so he joins forces with a woman gambler with a marvellous southern accent, and the two try and enter the game.", "popularity": 24.715, "original_title": "Maverick", "runtime": 127, "release_date": "1994-05-20", "vote_average": 6.864, "vote_count": 1453, "status": "Released", "tagline": "In their hands, a deck of cards was the only thing more dangerous than a gun.", "spoken_languages": "en", "cast": "Mel Gibson|Jodie Foster|James Garner|Graham Greene|Alfred Molina", "id": 9359}