{"overview": "Hong Kong cop Chan Ka-Kui returns, working with Interpol to track down and arrest an illegal weapons dealer. Chan later realizes that things are not as simple as they appear and soon finds himself to be a pawn of an organization posing as Russian intelligence.", "popularity": 20.173, "original_title": "\u8b66\u5bdf\u6545\u4e8b4\u4e4b\u7c21\u55ae\u4efb\u52d9", "runtime": 107, "release_date": "1996-02-10", "vote_average": 6.473, "vote_count": 426, "status": "Released", "tagline": "They thought they possessed the ultimate weapon. They hadn't counted on Jackie Chan.", "spoken_languages": "en|ru|uk|zh|cn", "cast": "Jackie Chan|Bill Tung|Jackson Liu|Annie Wu|Ailen Sit Chun-Wai", "id": 9404}