{"overview": "Archetypal buddy cops Riggs and Murtaugh are back for another round of high-stakes action, this time setting their collective sights on bringing down a former Los Angeles police lieutenant turned black market weapons dealer. Lorna Cole joins as the beautiful yet hardnosed internal affairs sergeant who catches Riggs's eye.", "popularity": 26.792, "original_title": "Lethal Weapon 3", "runtime": 118, "release_date": "1992-05-15", "vote_average": 6.697, "vote_count": 2650, "status": "Released", "tagline": "The magic is back again!", "spoken_languages": "en", "cast": "Mel Gibson|Danny Glover|Joe Pesci|Rene Russo|Stuart Wilson", "id": 943}