{"overview": "A sensitive girl is sent to an all-girls boarding school and develops a romantic attachment to one of her teachers.", "popularity": 9.921, "original_title": "M\u00e4dchen in Uniform", "runtime": 88, "release_date": "1931-11-27", "vote_average": 7.2, "vote_count": 74, "status": "Released", "tagline": "What is its strange appeal? Why does it stir the emotions?", "spoken_languages": "de", "cast": "Emilia Unda|Dorothea Wieck|Hedwig Schlichter|Hertha Thiele|Ellen Schwanneke", "id": 9653}