{"overview": "Sarah Jordan, an American living in London in 1984, is married to the son of a wealthy British industrialist. She encounters Nick Callahan, a renegade doctor, whose impassioned plea for help to support his relief efforts in war-torn Africa moves her deeply. As a result, Sarah embarks upon a journey of discovery that leads to danger, heartbreak and romance in the far corners of the world.", "popularity": 11.628, "original_title": "Beyond Borders", "runtime": 127, "release_date": "2003-10-23", "vote_average": 6.5, "vote_count": 375, "status": "Released", "tagline": "Where hope survives.", "spoken_languages": "en|am|km|de|ce", "cast": "Angelina Jolie|Clive Owen|Teri Polo|Linus Roache|Noah Emmerich", "id": 9839}