{"overview": "A fearless Secret Service agent will stop at nothing to bring down the counterfeiter who killed his partner.", "popularity": 16.127, "original_title": "To Live and Die in L.A.", "runtime": 116, "release_date": "1985-11-01", "vote_average": 7.105, "vote_count": 564, "status": "Released", "tagline": "A federal agent is dead. A killer is loose. And the City of Angels is about to explode.", "spoken_languages": "en|es", "cast": "William Petersen|Willem Dafoe|John Pankow|Debra Feuer|John Turturro", "id": 9846}