{"overview": "The irreverent host of a political satire talk show decides to run for president and expose corruption in Washington. His stunt goes further than he expects when he actually wins the election, but a software engineer suspects that a computer glitch is responsible for his surprising victory.", "popularity": 9.837, "original_title": "Man of the Year", "runtime": 115, "release_date": "2006-10-09", "vote_average": 5.906, "vote_count": 403, "status": "Released", "tagline": "Elections are made to be broken.", "spoken_languages": "en", "cast": "Robin Williams|Christopher Walken|Laura Linney|Lewis Black|Jeff Goldblum", "id": 9895}